mpx_genai_sdk/__init__.py
mpx_genai_sdk/_base_client.py
mpx_genai_sdk/_client.py
mpx_genai_sdk/_compat.py
mpx_genai_sdk/_constants.py
mpx_genai_sdk/_exceptions.py
mpx_genai_sdk/_files.py
mpx_genai_sdk/_models.py
mpx_genai_sdk/_qs.py
mpx_genai_sdk/_resource.py
mpx_genai_sdk/_response.py
mpx_genai_sdk/_streaming.py
mpx_genai_sdk/_types.py
mpx_genai_sdk/_version.py
mpx_genai_sdk/py.typed
mpx_genai_sdk/_utils/__init__.py
mpx_genai_sdk/_utils/_logs.py
mpx_genai_sdk/_utils/_proxy.py
mpx_genai_sdk/_utils/_reflection.py
mpx_genai_sdk/_utils/_resources_proxy.py
mpx_genai_sdk/_utils/_streams.py
mpx_genai_sdk/_utils/_sync.py
mpx_genai_sdk/_utils/_transform.py
mpx_genai_sdk/_utils/_typing.py
mpx_genai_sdk/_utils/_utils.py
mpx_genai_sdk/lib/.keep
mpx_genai_sdk/resources/__init__.py
mpx_genai_sdk/resources/assets.py
mpx_genai_sdk/resources/components.py
mpx_genai_sdk/resources/connection_test.py
mpx_genai_sdk/resources/functions.py
mpx_genai_sdk/resources/llms.py
mpx_genai_sdk/resources/status.py
mpx_genai_sdk/types/__init__.py
mpx_genai_sdk/types/asset_create_params.py
mpx_genai_sdk/types/component_optimize_params.py
mpx_genai_sdk/types/component_text2image_params.py
mpx_genai_sdk/types/connection_test_retrieve_response.py
mpx_genai_sdk/types/function_create_general_params.py
mpx_genai_sdk/types/function_imageto3d_params.py
mpx_genai_sdk/types/llm_call_params.py
mpx_genai_sdk/types/llm_image_query_params.py
mpx_genai_sdk/types/status_response_object.py
mpx_genai_sdk/types/shared/__init__.py
mpx_genai_sdk/types/shared/create_response_object.py
mpx_genai_sdk/types/shared/generate_response_object.py
mpx_genai_sdk-0.10.0.dist-info/METADATA
mpx_genai_sdk-0.10.0.dist-info/WHEEL
mpx_genai_sdk-0.10.0.dist-info/licenses/LICENSE
mpx_genai_sdk-0.10.0.dist-info/RECORD
